bussator/__init__.py
bussator/application.py
bussator/globals.py
bussator/plugin.py
bussator/plugins/__init__.py
bussator/plugins/dummy.py
bussator/plugins/isso.py
Bussator-0.2.dist-info/LICENSE
Bussator-0.2.dist-info/METADATA
Bussator-0.2.dist-info/WHEEL
Bussator-0.2.dist-info/top_level.txt
Bussator-0.2.dist-info/RECORD
