Metadata-Version: 2.1
Name: Bussator
Version: 0.2
Summary: A webmention receiver and publisher, written in Python (WSGI application)
Home-page: UNKNOWN
Author: Alberto Mardegan
Author-email: mardy@users.sourceforge.net
License: UNKNOWN
Platform: UNKNOWN
Classifier: Development Status :: 3 - Alpha
Classifier: Environment :: Web Environment
Classifier: Framework :: Pytest
Classifier: Intended Audience :: End Users/Desktop
Classifier: License :: OSI Approved :: GNU Affero General Public License v3
Classifier: Programming Language :: Python :: 3
Classifier: Topic :: Internet
Classifier: Topic :: Internet :: WWW/HTTP :: HTTP Servers
Classifier: Topic :: Internet :: WWW/HTTP :: WSGI :: Application
Requires-Dist: beautifulsoup4
Requires-Dist: html5lib
Requires-Dist: mf2py
Requires-Dist: python-dateutil
Requires-Dist: requests
